commandline_parsable.py
commandline_parsable-0.1.1.dist-info/DESCRIPTION.rst
commandline_parsable-0.1.1.dist-info/METADATA
commandline_parsable-0.1.1.dist-info/RECORD
commandline_parsable-0.1.1.dist-info/WHEEL
commandline_parsable-0.1.1.dist-info/metadata.json
commandline_parsable-0.1.1.dist-info/top_level.txt
