Metadata-Version: 2.0
Name: commandline-parsable
Version: 0.1.1
Summary: Choose subclass based on commandline options
Home-page: https://github.com/Bernhard10/commandline-parsable
Author: Bernhard Thiel
Author-email: thiel@tbi.univie.ac.at
License: UNKNOWN
Platform: UNKNOWN
Requires-Dist: regex
